README.rst
setup.py
marbaloo_mako/__init__.py
marbaloo_mako.egg-info/PKG-INFO
marbaloo_mako.egg-info/SOURCES.txt
marbaloo_mako.egg-info/dependency_links.txt
marbaloo_mako.egg-info/requires.txt
marbaloo_mako.egg-info/top_level.txt
test/testcase.py